ourocode/__init__.py
ourocode/__version__.py
ourocode/data/caracteristique_meca_acier.csv
ourocode/data/caracteristique_meca_bois.csv
ourocode/data/caracteristique_meca_panel.csv
ourocode/data/carte_action_region.csv
ourocode/data/coeff_psy.csv
ourocode/data/exploitation.csv
ourocode/data/gammaM.csv
ourocode/data/kdef.csv
ourocode/data/kfi.csv
ourocode/data/kmod.csv
ourocode/data/limite_fleche.csv
ourocode/data/qualite_acier.csv
ourocode/data/section_boulon.csv
ourocode/data/screenshot/C90_def.png
ourocode/data/screenshot/Kv_def.png
ourocode/data/screenshot/sign_convention.png
ourocode/data/sismique/categorie_importance.csv
ourocode/data/sismique/categorie_importance_ns.csv
ourocode/data/sismique/classe_sol.csv
ourocode/data/sismique/spectre_eleastique_h_type1.csv
ourocode/data/sismique/spectre_eleastique_h_type2.csv
ourocode/data/vent/vent_Cp_toiture_isolee_1_versant.csv
ourocode/data/vent/vent_Cp_toiture_isolee_1_versant.png
ourocode/data/vent/vent_Cp_toiture_isolee_2_versants.csv
ourocode/data/vent/vent_Cp_toiture_isolee_2_versants.png
ourocode/data/vent/vent_Cpe_mur_verticaux.csv
ourocode/data/vent/vent_Cpe_mur_verticaux.png
ourocode/data/vent/vent_Cpe_toiture_1_versant.png
ourocode/data/vent/vent_Cpe_toiture_1_versant_0_degres.csv
ourocode/data/vent/vent_Cpe_toiture_1_versant_180_degres.csv
ourocode/data/vent/vent_Cpe_toiture_1_versant_90_degres.csv
ourocode/data/vent/vent_Cpe_toiture_2_versants.png
ourocode/data/vent/vent_Cpe_toiture_2_versants_0_degres.csv
ourocode/data/vent/vent_Cpe_toiture_2_versants_90_degres.csv
ourocode/data/vent/vent_Cpe_toiture_terrasse.csv
ourocode/data/vent/vent_Cpe_toiture_terrasse.png
ourocode/data/vent/vent_Ffr.png
ourocode/eurocode/A0_Projet.py
ourocode/eurocode/EC0_Combinaison.py
ourocode/eurocode/EC1_Neige.py
ourocode/eurocode/EC1_Vent.py
ourocode/eurocode/EC3_Assemblage.py
ourocode/eurocode/EC3_Element_droit.py
ourocode/eurocode/EC5_Assemblage.py
ourocode/eurocode/EC5_CVT.py
ourocode/eurocode/EC5_Element_droit.py
ourocode-1.7.6.dist-info/licenses/LICENSE
ourocode-1.7.6.dist-info/METADATA
ourocode-1.7.6.dist-info/WHEEL
ourocode-1.7.6.dist-info/top_level.txt
ourocode-1.7.6.dist-info/RECORD
