Metadata-Version: 2.4
Name: ourocode
Version: 1.7.6
Summary: Ceci est un catalogue de fonction permettant une utilisation rapide pour la réalisation de note de calcul personnalisée.
Author-email: Anthony PARISOT <contact@ourea-structure.fr>
License-Expression: Apache-2.0
Project-URL: Homepage, https://github.com/AnthonyPrst/ourocode
Classifier: Programming Language :: Python :: 3.12
Classifier: Operating System :: OS Independent
Requires-Python: >=3.12
License-File: LICENSE
Requires-Dist: handcalcs
Requires-Dist: forallpeople
Requires-Dist: PyNiteFEA
Requires-Dist: pyvista[all,trame]
Requires-Dist: PySide6
Requires-Dist: pandas
Requires-Dist: Pillow
Provides-Extra: dev
Requires-Dist: black; extra == "dev"
Provides-Extra: test
Requires-Dist: pytest; extra == "test"
Requires-Dist: pytest-cov; extra == "test"
Requires-Dist: coverage; extra == "test"
Dynamic: license-file
